BankAccountSystem/__init__.py
BankAccountSystem_XiaCatQ-1.0.dist-info/LICENSE.txt
BankAccountSystem_XiaCatQ-1.0.dist-info/METADATA
BankAccountSystem_XiaCatQ-1.0.dist-info/WHEEL
BankAccountSystem_XiaCatQ-1.0.dist-info/top_level.txt
BankAccountSystem_XiaCatQ-1.0.dist-info/RECORD
