Metadata-Version: 2.1
Name: BankAccountSystem-XiaCatQ
Version: 1.0
Summary: A system to simulate bank GUI python package
Home-page: https://github.com/XiaCatQ/project-step-3-chenziying/tree/main/BankAccountSystem
Author: XiaCatQ
Author-email: boziying@gmail.com
License: MIT
Platform: UNKNOWN
License-File: LICENSE.txt
